swedeb_demo/__init__.py
swedeb_demo/api/__init__.py
swedeb_demo/api/dummy_api.py
swedeb_demo/api/parlaclarin/__init__.py
swedeb_demo/api/parlaclarin/__paths__.py
swedeb_demo/api/parlaclarin/codecs.py
swedeb_demo/api/parlaclarin/speech_text.py
swedeb_demo/api/parlaclarin/trends_data.py
swedeb_demo/api/parlaclarin/utility.py
swedeb_demo/api/trends-demo.ipynb
swedeb_demo/api/westac/__init__.py
swedeb_demo/api/westac/riksprot/__init__.py
swedeb_demo/api/westac/riksprot/kb_labb/convert_1800.py
swedeb_demo/api/westac/riksprot/parlaclarin/__init__.py
swedeb_demo/api/westac/riksprot/parlaclarin/codecs.py
swedeb_demo/api/westac/riksprot/parlaclarin/purgatory/metadata.py
swedeb_demo/api/westac/riksprot/parlaclarin/speech_text.py
swedeb_demo/api/westac/riksprot/parlaclarin/utility.py
swedeb_demo/components/__init__.py
swedeb_demo/components/component_texts.py
swedeb_demo/components/gender_checkboxes.py
swedeb_demo/components/kwic_tab.py
swedeb_demo/components/meta_data_display.py
swedeb_demo/components/party_dropdown.py
swedeb_demo/components/speaker_dropdown.py
swedeb_demo/components/speech_display_mixin.py
swedeb_demo/components/table_results.py
swedeb_demo/components/tool_tab.py
swedeb_demo/components/whole_speeches_tab.py
swedeb_demo/components/word_trends_tab.py
swedeb_demo/main_page_shared_filter.py
swedeb_demo/props.json
swedeb_explorer-0.1.15.dist-info/METADATA
swedeb_explorer-0.1.15.dist-info/WHEEL
swedeb_explorer-0.1.15.dist-info/RECORD
